jsm_asset/__init__.py
jsm_asset/aql.py
jsm_asset/asset.py
jsm_asset/exceptions.py
jsm_asset/metadata.py
jsm_asset/object.py
jsm_asset/schema.py
jsm_asset/session.py
jsm_asset/util.py
jsm_asset-0.1.2.dist-info/METADATA
jsm_asset-0.1.2.dist-info/WHEEL
jsm_asset-0.1.2.dist-info/licenses/LICENSE
jsm_asset-0.1.2.dist-info/RECORD
