Metadata-Version: 2.4
Name: jsm_asset
Version: 0.1.2
Summary: A python-based interface to the JSM Asset API
Author-email: Sean Broestl <broestls@gmail.com>
License-Expression: MIT
License-File: LICENSE
Requires-Python: >=3.13
Requires-Dist: requests<3,>=2.28.1
